odoo/addons/l10n_ch_pain_base/README.rst
odoo/addons/l10n_ch_pain_base/__init__.py
odoo/addons/l10n_ch_pain_base/__manifest__.py
odoo/addons/l10n_ch_pain_base/i18n/de.po
odoo/addons/l10n_ch_pain_base/i18n/fr.po
odoo/addons/l10n_ch_pain_base/i18n/it.po
odoo/addons/l10n_ch_pain_base/migrations/11.0.1.0.0/post-migration.py
odoo/addons/l10n_ch_pain_base/models/__init__.py
odoo/addons/l10n_ch_pain_base/models/account_move_line.py
odoo/addons/l10n_ch_pain_base/models/account_payment_line.py
odoo/addons/l10n_ch_pain_base/models/account_payment_order.py
odoo/addons/l10n_ch_pain_base/views/account_payment_line.xml
odoo/addons/l10n_ch_pain_base/views/bank_payment_line.xml
odoo11_addon_l10n_ch_pain_base-11.0.1.0.0.dist-info/DESCRIPTION.rst
odoo11_addon_l10n_ch_pain_base-11.0.1.0.0.dist-info/METADATA
odoo11_addon_l10n_ch_pain_base-11.0.1.0.0.dist-info/RECORD
odoo11_addon_l10n_ch_pain_base-11.0.1.0.0.dist-info/WHEEL
odoo11_addon_l10n_ch_pain_base-11.0.1.0.0.dist-info/metadata.json
odoo11_addon_l10n_ch_pain_base-11.0.1.0.0.dist-info/top_level.txt
