Metadata-Version: 2.0
Name: odoo11-addon-l10n-ch-pain-base
Version: 11.0.1.0.0
Summary: ISO 20022 base module for Switzerland
Home-page: UNKNOWN
Author: Akretion,Camptocamp,Odoo Community Association (OCA)
Author-email: support@odoo-community.org
License: AGPL-3
Platform: UNKNOWN
Classifier: Programming Language :: Python
Classifier: Framework :: Odoo
Classifier: License :: OSI Approved :: GNU Affero General Public License v3
Requires-Python: >=2.7, !=3.0.*, !=3.1.*, !=3.2.*, !=3.3.*, !=3.4.*
Requires-Dist: odoo (<11.1dev,>=11.0a)
Requires-Dist: odoo11-addon-account-banking-pain-base
Requires-Dist: odoo11-addon-l10n-ch-base-bank
